colorPrintConsole/ColorPrint.py
colorPrintConsole/__init__.py
colorprintconsole-1.0.8.dist-info/licenses/LICENSE
colorprintconsole-1.0.8.dist-info/METADATA
colorprintconsole-1.0.8.dist-info/WHEEL
colorprintconsole-1.0.8.dist-info/top_level.txt
colorprintconsole-1.0.8.dist-info/RECORD
