Metadata-Version: 2.4
Name: colorPrintConsole
Version: 1.0.8
Summary: 一个用于在终端中打印彩色文字的包
Author-email: 苏寅 <suyin_long@163.com>
License:                                  Apache License
Project-URL: Homepage, https://gitee.com/suyin-long/color-print
Classifier: Programming Language :: Python :: 3
Classifier: License :: OSI Approved :: MIT License
Classifier: Operating System :: OS Independent
Requires-Python: >=3.6
License-File: LICENSE
Dynamic: license-file
